LICENSE.rst
README.md
setup.cfg
setup.py
ravop/__init__.py
ravop/config.py
ravop/globals.py
ravop/logger.py
ravop/singleton_utils.py
ravop/strings.py
ravop/utils.py
ravop.egg-info/PKG-INFO
ravop.egg-info/SOURCES.txt
ravop.egg-info/dependency_links.txt
ravop.egg-info/requires.txt
ravop.egg-info/top_level.txt
ravop/core/__init__.py
ravop/core/ftp_client.py