Metadata-Version: 2.1
Name: ravop
Version: 0.12
Summary: UNKNOWN
Home-page: https://github.com/ravenprotocol/ravop
Author: Raven Protocol
Author-email: kailash@ravenprotocol.com
License: MIT
Keywords: Ravop,requester library
Platform: UNKNOWN
License-File: LICENSE.rst
